transfersh.py
transfersh_cli-1.1.0.dist-info/LICENSE
transfersh_cli-1.1.0.dist-info/METADATA
transfersh_cli-1.1.0.dist-info/WHEEL
transfersh_cli-1.1.0.dist-info/entry_points.txt
transfersh_cli-1.1.0.dist-info/top_level.txt
transfersh_cli-1.1.0.dist-info/RECORD
