Metadata-Version: 2.1
Name: transfersh-cli
Version: 1.1.0
Summary: Client to upload files to the transfer.sh service
Home-page: https://github.com/tanrax/transfersh-cli
Author: Andros Fenollosa
Author-email: andros@fenollosa.email
License: UNKNOWN
Keywords: transfer,upload,client
Platform: UNKNOWN
Classifier: Programming Language :: Python :: 3
Classifier: License :: OSI Approved :: MIT License
Classifier: Operating System :: OS Independent
Requires-Python: >3.6
Requires-Dist: Click (>=6.7)
Requires-Dist: pyperclip (>=1.6.4)
Requires-Dist: requests (>=2.19.1)
